bibverse/__init__.py
bibverse/__main__.py
bibverse-1.3.dist-info/LICENSE
bibverse-1.3.dist-info/METADATA
bibverse-1.3.dist-info/WHEEL
bibverse-1.3.dist-info/entry_points.txt
bibverse-1.3.dist-info/top_level.txt
bibverse-1.3.dist-info/RECORD
