Metadata-Version: 2.1
Name: bibverse
Version: 1.3
Summary: A simple cli tool to get the bible verse of the day
Home-page: https://github.com/LordUbuntu/bibverse
Author: Jacobus Burger
Author-email: therealjacoburger@gmail.com
License: MIT
Keywords: python,bible,cli
Platform: any
Classifier: Development Status :: 5 - Production/Stable
Classifier: Programming Language :: Python :: 3.10
Classifier: Operating System :: OS Independent
Classifier: Topic :: Utilities
Classifier: Environment :: Console
Classifier: License :: OSI Approved :: MIT License
Requires-Python: >=3.10
License-File: LICENSE
Requires-Dist: beautifulsoup4 (==4.12.2)
Requires-Dist: bs4 (==0.0.1)
Requires-Dist: requests (==2.30.0)
Provides-Extra: dev
Requires-Dist: pytest (>=7.2) ; extra == 'dev'
Requires-Dist: twine (>=4.0.2) ; extra == 'dev'
